announcements/__init__.py
announcements/admin.py
announcements/apps.py
announcements/context_processors.py
announcements/defaults.py
announcements/models.py
announcements/urls.py
announcements/views.py
announcements/migrations/0001_initial.py
announcements/migrations/0002_add_extra_content_video_link_and_announcement_type_fields.py
announcements/migrations/0003_template_field_refactor.py
announcements/migrations/0004_expire_days_default.py
announcements/migrations/0005_default_start_day.py
announcements/migrations/0006_convert_textfield_to_richtextfield.py
announcements/migrations/0007_siterelated_announcement.py
announcements/migrations/0008_sort_by_date_start.py
announcements/migrations/__init__.py
announcements/static/js/announcements.js
announcements/static/js/js.cookie.js
announcements/templates/announcements/announcements.html
announcements/templatetags/__init__.py
announcements/templatetags/announcements_tags.py
mezzanine_announcements-3.3.0.dist-info/LICENSE
mezzanine_announcements-3.3.0.dist-info/METADATA
mezzanine_announcements-3.3.0.dist-info/WHEEL
mezzanine_announcements-3.3.0.dist-info/top_level.txt
mezzanine_announcements-3.3.0.dist-info/RECORD
