Metadata-Version: 2.1
Name: mezzanine-announcements
Version: 3.3.0
Summary: Site-wide announcements for Mezzanine websites
Home-page: http://github.com/unplugstudio/mezzanine-announcements
Author: Unplug Studio
Author-email: developers@unplug.studio
License: UNKNOWN
Keywords: django,mezzanine,announcement,popup,banner,alert
Platform: UNKNOWN
Classifier: License :: OSI Approved :: MIT License
Classifier: Operating System :: OS Independent
Classifier: Programming Language :: Python
Classifier: Programming Language :: Python :: 2
Classifier: Programming Language :: Python :: 2.7
Classifier: Programming Language :: Python :: 3
Classifier: Programming Language :: Python :: 3.6
Classifier: Programming Language :: Python :: 3.7
Classifier: Programming Language :: Python :: 3.8
Requires-Python: !=3.0.*,!=3.1.*,!=3.2.*,!=3.3.*,!=3.4.*,!=3.5*,>=2.7
License-File: LICENSE
Requires-Dist: mezzanine (>=4)
Requires-Dist: django (>=1.8)
Provides-Extra: testing
Requires-Dist: django-dynamic-fixture (<4,>=3) ; extra == 'testing'
Requires-Dist: django-functest (<2,>=1) ; extra == 'testing'
Requires-Dist: pytest-django (<4,>=3) ; extra == 'testing'
